{"note":"This file is an internal implementation detail to speed up HTML report generation. Its format can change at any time. You might be looking for the JSON report: https://coverage.rtfd.io/cmd.html#cmd-json","format":5,"version":"7.6.9","globals":"bc551f8060f36b5af2cc8f8a9ee67267","files":{"z_5f5a17c013354698___init___py":{"hash":"baa53744b4f186a4f1a98e1d13b4ff64","index":{"url":"z_5f5a17c013354698___init___py.html","file":"app/__init__.py","description":"","nums":{"precision":0,"n_files":1,"n_statements":2,"n_excluded":0,"n_missing":0,"n_branches":0,"n_partial_branches":0,"n_missing_branches":0}}},"z_122122f3b0c8831a___init___py":{"hash":"79742e72e5559d5e6064954a8326c19a","index":{"url":"z_122122f3b0c8831a___init___py.html","file":"app/core/base/__init__.py","description":"","nums":{"precision":0,"n_files":1,"n_statements":7,"n_excluded":0,"n_missing":0,"n_branches":0,"n_partial_branches":0,"n_missing_branches":0}}},"z_122122f3b0c8831a_base_input_dto_py":{"hash":"13f76cdfdfb57b562552c6fa60c0f1b4","index":{"url":"z_122122f3b0c8831a_base_input_dto_py.html","file":"app/core/base/base_input_dto.py","description":"","nums":{"precision":0,"n_files":1,"n_statements":3,"n_excluded":0,"n_missing":0,"n_branches":0,"n_partial_branches":0,"n_missing_branches":0}}},"z_122122f3b0c8831a_base_output_dto_py":{"hash":"6f84eaab5b914d1d7361feb18b39c8c9","index":{"url":"z_122122f3b0c8831a_base_output_dto_py.html","file":"app/core/base/base_output_dto.py","description":"","nums":{"precision":0,"n_files":1,"n_statements":3,"n_excluded":0,"n_missing":0,"n_branches":0,"n_partial_branches":0,"n_missing_branches":0}}},"z_122122f3b0c8831a_base_request_py":{"hash":"1609ae9ecc4b1ab97ea6bdb5baeb2067","index":{"url":"z_122122f3b0c8831a_base_request_py.html","file":"app/core/base/base_request.py","description":"","nums":{"precision":0,"n_files":1,"n_statements":6,"n_excluded":0,"n_missing":0,"n_branches":0,"n_partial_branches":0,"n_missing_branches":0}}},"z_122122f3b0c8831a_base_response_py":{"hash":"b1e2df970a8305a7c638dc7a7d900d38","index":{"url":"z_122122f3b0c8831a_base_response_py.html","file":"app/core/base/base_response.py","description":"","nums":{"precision":0,"n_files":1,"n_statements":6,"n_excluded":0,"n_missing":0,"n_branches":0,"n_partial_branches":0,"n_missing_branches":0}}},"z_122122f3b0c8831a_base_uow_py":{"hash":"4068929815b1b7c003c455c3e7ab8bf3","index":{"url":"z_122122f3b0c8831a_base_uow_py.html","file":"app/core/base/base_uow.py","description":"","nums":{"precision":0,"n_files":1,"n_statements":14,"n_excluded":0,"n_missing":0,"n_branches":0,"n_partial_branches":0,"n_missing_branches":0}}},"z_122122f3b0c8831a_base_usecase_py":{"hash":"ec1d5a3785214a820ee10371bad8eb7d","index":{"url":"z_122122f3b0c8831a_base_usecase_py.html","file":"app/core/base/base_usecase.py","description":"","nums":{"precision":0,"n_files":1,"n_statements":10,"n_excluded":2,"n_missing":2,"n_branches":0,"n_partial_branches":0,"n_missing_branches":0}}},"z_122122f3b0c8831a_base_value_object_py":{"hash":"753e76cd8d7e7cbf5547a60ed4a6a478","index":{"url":"z_122122f3b0c8831a_base_value_object_py.html","file":"app/core/base/base_value_object.py","description":"","nums":{"precision":0,"n_files":1,"n_statements":3,"n_excluded":2,"n_missing":0,"n_branches":0,"n_partial_branches":0,"n_missing_branches":0}}},"z_9847d120e6674b7d___init___py":{"hash":"1d8d8cf553f07ce53d549aebf2230dc2","index":{"url":"z_9847d120e6674b7d___init___py.html","file":"app/core/middleware/__init__.py","description":"","nums":{"precision":0,"n_files":1,"n_statements":2,"n_excluded":0,"n_missing":0,"n_branches":0,"n_partial_branches":0,"n_missing_branches":0}}},"z_9847d120e6674b7d_exception_handling_middleware_py":{"hash":"eccdf5c6814f39bb62a7b88878259833","index":{"url":"z_9847d120e6674b7d_exception_handling_middleware_py.html","file":"app/core/middleware/exception_handling_middleware.py","description":"","nums":{"precision":0,"n_files":1,"n_statements":11,"n_excluded":0,"n_missing":0,"n_branches":0,"n_partial_branches":0,"n_missing_branches":0}}},"z_9847d120e6674b7d_logging_middleware_py":{"hash":"d10b920939df3b8f14f6521461097738","index":{"url":"z_9847d120e6674b7d_logging_middleware_py.html","file":"app/core/middleware/logging_middleware.py","description":"","nums":{"precision":0,"n_files":1,"n_statements":20,"n_excluded":0,"n_missing":0,"n_branches":0,"n_partial_branches":0,"n_missing_branches":0}}},"z_3c86c2c8ab922746___init___py":{"hash":"573a85fdadbfaa3f94aafd1437e962c1","index":{"url":"z_3c86c2c8ab922746___init___py.html","file":"app/ddd/application/dto/user/__init__.py","description":"","nums":{"precision":0,"n_files":1,"n_statements":2,"n_excluded":0,"n_missing":0,"n_branches":0,"n_partial_branches":0,"n_missing_branches":0}}},"z_3c86c2c8ab922746_user_input_dto_py":{"hash":"1134a6ca03560eb7a14869d71577b96d","index":{"url":"z_3c86c2c8ab922746_user_input_dto_py.html","file":"app/ddd/application/dto/user/user_input_dto.py","description":"","nums":{"precision":0,"n_files":1,"n_statements":15,"n_excluded":3,"n_missing":0,"n_branches":0,"n_partial_branches":0,"n_missing_branches":0}}},"z_3c86c2c8ab922746_user_output_dto_py":{"hash":"ca7624d3cf46e827f4803d7ebec63c7e","index":{"url":"z_3c86c2c8ab922746_user_output_dto_py.html","file":"app/ddd/application/dto/user/user_output_dto.py","description":"","nums":{"precision":0,"n_files":1,"n_statements":15,"n_excluded":3,"n_missing":0,"n_branches":0,"n_partial_branches":0,"n_missing_branches":0}}},"z_cba60e2e75817499___init___py":{"hash":"4e6acdf00d50fdeb7cdfc73f1fccfd8c","index":{"url":"z_cba60e2e75817499___init___py.html","file":"app/ddd/application/uow/__init__.py","description":"","nums":{"precision":0,"n_files":1,"n_statements":1,"n_excluded":0,"n_missing":0,"n_branches":0,"n_partial_branches":0,"n_missing_branches":0}}},"z_cba60e2e75817499_user_uow_py":{"hash":"001e7f00d1e3b3687abcb8557033a59d","index":{"url":"z_cba60e2e75817499_user_uow_py.html","file":"app/ddd/application/uow/user_uow.py","description":"","nums":{"precision":0,"n_files":1,"n_statements":7,"n_excluded":0,"n_missing":0,"n_branches":0,"n_partial_branches":0,"n_missing_branches":0}}},"z_138f4a5a6c14388b___init___py":{"hash":"61afeaaf0ad18cd8662b026395f03e08","index":{"url":"z_138f4a5a6c14388b___init___py.html","file":"app/ddd/application/usecase/user/__init__.py","description":"","nums":{"precision":0,"n_files":1,"n_statements":5,"n_excluded":0,"n_missing":0,"n_branches":0,"n_partial_branches":0,"n_missing_branches":0}}},"z_138f4a5a6c14388b_base_user_usecase_py":{"hash":"dc423a038f1872db731f1c572d584efd","index":{"url":"z_138f4a5a6c14388b_base_user_usecase_py.html","file":"app/ddd/application/usecase/user/base_user_usecase.py","description":"","nums":{"precision":0,"n_files":1,"n_statements":5,"n_excluded":0,"n_missing":0,"n_branches":0,"n_partial_branches":0,"n_missing_branches":0}}},"z_138f4a5a6c14388b_create_user_usecase_py":{"hash":"77cfebba180fdb0f7087cf18412756d6","index":{"url":"z_138f4a5a6c14388b_create_user_usecase_py.html","file":"app/ddd/application/usecase/user/create_user_usecase.py","description":"","nums":{"precision":0,"n_files":1,"n_statements":9,"n_excluded":0,"n_missing":0,"n_branches":0,"n_partial_branches":0,"n_missing_branches":0}}},"z_138f4a5a6c14388b_delete_user_usecase_py":{"hash":"8cdc4ac88f98e64a117c70cf2d56c977","index":{"url":"z_138f4a5a6c14388b_delete_user_usecase_py.html","file":"app/ddd/application/usecase/user/delete_user_usecase.py","description":"","nums":{"precision":0,"n_files":1,"n_statements":9,"n_excluded":0,"n_missing":0,"n_branches":0,"n_partial_branches":0,"n_missing_branches":0}}},"z_138f4a5a6c14388b_get_user_usecase_py":{"hash":"6132e1dcdca2214f81b0fb05de8b88fd","index":{"url":"z_138f4a5a6c14388b_get_user_usecase_py.html","file":"app/ddd/application/usecase/user/get_user_usecase.py","description":"","nums":{"precision":0,"n_files":1,"n_statements":8,"n_excluded":0,"n_missing":0,"n_branches":0,"n_partial_branches":0,"n_missing_branches":0}}},"z_138f4a5a6c14388b_patch_user_usecase_py":{"hash":"a08930b44512449672623e3abb2190f1","index":{"url":"z_138f4a5a6c14388b_patch_user_usecase_py.html","file":"app/ddd/application/usecase/user/patch_user_usecase.py","description":"","nums":{"precision":0,"n_files":1,"n_statements":11,"n_excluded":0,"n_missing":0,"n_branches":0,"n_partial_branches":0,"n_missing_branches":0}}},"z_138f4a5a6c14388b_query_user_usecase_py":{"hash":"c8250d86d3cb596e9ab1ada429e23eb6","index":{"url":"z_138f4a5a6c14388b_query_user_usecase_py.html","file":"app/ddd/application/usecase/user/query_user_usecase.py","description":"","nums":{"precision":0,"n_files":1,"n_statements":6,"n_excluded":0,"n_missing":0,"n_branches":0,"n_partial_branches":0,"n_missing_branches":0}}},"z_1f6b4b5bde27e51a___init___py":{"hash":"1ef9b557c17095f23c0cc2319a3c6a4b","index":{"url":"z_1f6b4b5bde27e51a___init___py.html","file":"app/ddd/domain/__init__.py","description":"","nums":{"precision":0,"n_files":1,"n_statements":3,"n_excluded":0,"n_missing":0,"n_branches":0,"n_partial_branches":0,"n_missing_branches":0}}},"z_77cf29a673426669___init___py":{"hash":"fae01becfa1f743a52455099b60666c4","index":{"url":"z_77cf29a673426669___init___py.html","file":"app/ddd/domain/error/__init__.py","description":"","nums":{"precision":0,"n_files":1,"n_statements":1,"n_excluded":0,"n_missing":0,"n_branches":0,"n_partial_branches":0,"n_missing_branches":0}}},"z_77cf29a673426669_user_error_py":{"hash":"dc649c8398b463e984eb51bca0c157ee","index":{"url":"z_77cf29a673426669_user_error_py.html","file":"app/ddd/domain/error/user_error.py","description":"","nums":{"precision":0,"n_files":1,"n_statements":2,"n_excluded":2,"n_missing":0,"n_branches":0,"n_partial_branches":0,"n_missing_branches":0}}},"z_e953688ecee0502e___init___py":{"hash":"ab5a77c34763ea10d6b899711f96df53","index":{"url":"z_e953688ecee0502e___init___py.html","file":"app/ddd/domain/model/__init__.py","description":"","nums":{"precision":0,"n_files":1,"n_statements":1,"n_excluded":0,"n_missing":0,"n_branches":0,"n_partial_branches":0,"n_missing_branches":0}}},"z_e953688ecee0502e_user_py":{"hash":"4f8449bdcfc3b39040d88840531e76fe","index":{"url":"z_e953688ecee0502e_user_py.html","file":"app/ddd/domain/model/user.py","description":"","nums":{"precision":0,"n_files":1,"n_statements":20,"n_excluded":1,"n_missing":0,"n_branches":0,"n_partial_branches":0,"n_missing_branches":0}}},"z_91915620dc2765cb___init___py":{"hash":"b4186907c922d67b2e56a3386acbaf42","index":{"url":"z_91915620dc2765cb___init___py.html","file":"app/ddd/domain/repository/__init__.py","description":"","nums":{"precision":0,"n_files":1,"n_statements":1,"n_excluded":0,"n_missing":0,"n_branches":0,"n_partial_branches":0,"n_missing_branches":0}}},"z_91915620dc2765cb_user_repository_py":{"hash":"172fca680a78169c2017705994de0af6","index":{"url":"z_91915620dc2765cb_user_repository_py.html","file":"app/ddd/domain/repository/user_repository.py","description":"","nums":{"precision":0,"n_files":1,"n_statements":16,"n_excluded":6,"n_missing":0,"n_branches":0,"n_partial_branches":0,"n_missing_branches":0}}},"z_de87f66bf0397df0___init___py":{"hash":"72b972ba10d253ac709f767238df664f","index":{"url":"z_de87f66bf0397df0___init___py.html","file":"app/ddd/infrastructure/database/__init__.py","description":"","nums":{"precision":0,"n_files":1,"n_statements":1,"n_excluded":0,"n_missing":0,"n_branches":0,"n_partial_branches":0,"n_missing_branches":0}}},"z_de87f66bf0397df0_db_py":{"hash":"d5d453b28554e3073041d76f52fcc4e0","index":{"url":"z_de87f66bf0397df0_db_py.html","file":"app/ddd/infrastructure/database/db.py","description":"","nums":{"precision":0,"n_files":1,"n_statements":15,"n_excluded":0,"n_missing":0,"n_branches":0,"n_partial_branches":0,"n_missing_branches":0}}},"z_6fde700c19aef8cc___init___py":{"hash":"eac5ad7ead16e80ac10548b503b388fe","index":{"url":"z_6fde700c19aef8cc___init___py.html","file":"app/ddd/infrastructure/repository/__init__.py","description":"","nums":{"precision":0,"n_files":1,"n_statements":1,"n_excluded":0,"n_missing":0,"n_branches":0,"n_partial_branches":0,"n_missing_branches":0}}},"z_6fde700c19aef8cc_user_repository_impl_py":{"hash":"3f019207987e5b126e0cd16c4644471f","index":{"url":"z_6fde700c19aef8cc_user_repository_impl_py.html","file":"app/ddd/infrastructure/repository/user_repository_impl.py","description":"","nums":{"precision":0,"n_files":1,"n_statements":38,"n_excluded":0,"n_missing":1,"n_branches":0,"n_partial_branches":0,"n_missing_branches":0}}},"z_1e22fe08fe415060___init___py":{"hash":"a58b0f1683cda68003600d08d6be5c3d","index":{"url":"z_1e22fe08fe415060___init___py.html","file":"app/ddd/infrastructure/uow/__init__.py","description":"","nums":{"precision":0,"n_files":1,"n_statements":1,"n_excluded":0,"n_missing":0,"n_branches":0,"n_partial_branches":0,"n_missing_branches":0}}},"z_1e22fe08fe415060_user_uow_impl_py":{"hash":"9ce9838ed972816950d5250ba719b215","index":{"url":"z_1e22fe08fe415060_user_uow_impl_py.html","file":"app/ddd/infrastructure/uow/user_uow_impl.py","description":"","nums":{"precision":0,"n_files":1,"n_statements":6,"n_excluded":0,"n_missing":0,"n_branches":0,"n_partial_branches":0,"n_missing_branches":0}}},"z_d642dc1439405641___init___py":{"hash":"ca786cfdddde582246c2f37413b7ceed","index":{"url":"z_d642dc1439405641___init___py.html","file":"app/ddd/presentation/endpoint/__init__.py","description":"","nums":{"precision":0,"n_files":1,"n_statements":1,"n_excluded":0,"n_missing":0,"n_branches":0,"n_partial_branches":0,"n_missing_branches":0}}},"z_8389f7c7aa0186e8___init___py":{"hash":"27ec66a8e0f9b4ba6f9ae472cf179f34","index":{"url":"z_8389f7c7aa0186e8___init___py.html","file":"app/ddd/presentation/endpoint/health/__init__.py","description":"","nums":{"precision":0,"n_files":1,"n_statements":2,"n_excluded":0,"n_missing":0,"n_branches":0,"n_partial_branches":0,"n_missing_branches":0}}},"z_8389f7c7aa0186e8_get_health_py":{"hash":"f12e3a383cc0a39e61e8dbe6424a9a3b","index":{"url":"z_8389f7c7aa0186e8_get_health_py.html","file":"app/ddd/presentation/endpoint/health/get_health.py","description":"","nums":{"precision":0,"n_files":1,"n_statements":5,"n_excluded":0,"n_missing":0,"n_branches":0,"n_partial_branches":0,"n_missing_branches":0}}},"z_8389f7c7aa0186e8_router_py":{"hash":"d26554904781d7005d9890eea4818c85","index":{"url":"z_8389f7c7aa0186e8_router_py.html","file":"app/ddd/presentation/endpoint/health/router.py","description":"","nums":{"precision":0,"n_files":1,"n_statements":2,"n_excluded":0,"n_missing":0,"n_branches":0,"n_partial_branches":0,"n_missing_branches":0}}},"z_82a1327639cdecb1___init___py":{"hash":"16b699f33966b0e820fbb2810cd49e47","index":{"url":"z_82a1327639cdecb1___init___py.html","file":"app/ddd/presentation/endpoint/pages/__init__.py","description":"","nums":{"precision":0,"n_files":1,"n_statements":2,"n_excluded":0,"n_missing":0,"n_branches":0,"n_partial_branches":0,"n_missing_branches":0}}},"z_82a1327639cdecb1_get_pages_streaming_py":{"hash":"4eebc6638776955b0081496e46f53205","index":{"url":"z_82a1327639cdecb1_get_pages_streaming_py.html","file":"app/ddd/presentation/endpoint/pages/get_pages_streaming.py","description":"","nums":{"precision":0,"n_files":1,"n_statements":7,"n_excluded":0,"n_missing":0,"n_branches":0,"n_partial_branches":0,"n_missing_branches":0}}},"z_82a1327639cdecb1_router_py":{"hash":"d26554904781d7005d9890eea4818c85","index":{"url":"z_82a1327639cdecb1_router_py.html","file":"app/ddd/presentation/endpoint/pages/router.py","description":"","nums":{"precision":0,"n_files":1,"n_statements":2,"n_excluded":0,"n_missing":0,"n_branches":0,"n_partial_branches":0,"n_missing_branches":0}}},"z_d642dc1439405641_router_py":{"hash":"459ec8bdf0a9ee7ea47944d69310be57","index":{"url":"z_d642dc1439405641_router_py.html","file":"app/ddd/presentation/endpoint/router.py","description":"","nums":{"precision":0,"n_files":1,"n_statements":6,"n_excluded":0,"n_missing":0,"n_branches":0,"n_partial_branches":0,"n_missing_branches":0}}},"z_7c66ddcc68815347___init___py":{"hash":"3ddfa20a545937e713fa5a32a85b2ab0","index":{"url":"z_7c66ddcc68815347___init___py.html","file":"app/ddd/presentation/endpoint/user/__init__.py","description":"","nums":{"precision":0,"n_files":1,"n_statements":6,"n_excluded":0,"n_missing":0,"n_branches":0,"n_partial_branches":0,"n_missing_branches":0}}},"z_7c66ddcc68815347_create_user_py":{"hash":"b033b5729cb791523bf29662469919dd","index":{"url":"z_7c66ddcc68815347_create_user_py.html","file":"app/ddd/presentation/endpoint/user/create_user.py","description":"","nums":{"precision":0,"n_files":1,"n_statements":15,"n_excluded":0,"n_missing":0,"n_branches":0,"n_partial_branches":0,"n_missing_branches":0}}},"z_7c66ddcc68815347_delete_user_py":{"hash":"bb80935a37c4b4bc9abea40c0179ee89","index":{"url":"z_7c66ddcc68815347_delete_user_py.html","file":"app/ddd/presentation/endpoint/user/delete_user.py","description":"","nums":{"precision":0,"n_files":1,"n_statements":15,"n_excluded":0,"n_missing":0,"n_branches":0,"n_partial_branches":0,"n_missing_branches":0}}},"z_7c66ddcc68815347_get_user_py":{"hash":"a7443fafe6c8fc99dff07424ad4b827d","index":{"url":"z_7c66ddcc68815347_get_user_py.html","file":"app/ddd/presentation/endpoint/user/get_user.py","description":"","nums":{"precision":0,"n_files":1,"n_statements":21,"n_excluded":0,"n_missing":0,"n_branches":0,"n_partial_branches":0,"n_missing_branches":0}}},"z_7c66ddcc68815347_patch_user_py":{"hash":"41454c4b0869bf0aa16e58432517542a","index":{"url":"z_7c66ddcc68815347_patch_user_py.html","file":"app/ddd/presentation/endpoint/user/patch_user.py","description":"","nums":{"precision":0,"n_files":1,"n_statements":15,"n_excluded":0,"n_missing":0,"n_branches":0,"n_partial_branches":0,"n_missing_branches":0}}},"z_7c66ddcc68815347_query_users_py":{"hash":"fc6c56784fd042da3fc7c5ba9818e0a9","index":{"url":"z_7c66ddcc68815347_query_users_py.html","file":"app/ddd/presentation/endpoint/user/query_users.py","description":"","nums":{"precision":0,"n_files":1,"n_statements":15,"n_excluded":0,"n_missing":0,"n_branches":0,"n_partial_branches":0,"n_missing_branches":0}}},"z_7c66ddcc68815347_router_py":{"hash":"d26554904781d7005d9890eea4818c85","index":{"url":"z_7c66ddcc68815347_router_py.html","file":"app/ddd/presentation/endpoint/user/router.py","description":"","nums":{"precision":0,"n_files":1,"n_statements":2,"n_excluded":0,"n_missing":0,"n_branches":0,"n_partial_branches":0,"n_missing_branches":0}}},"z_58015e6836bfb4e5___init___py":{"hash":"3eacec4a0a1a5d8a6660363ddc8b21cd","index":{"url":"z_58015e6836bfb4e5___init___py.html","file":"app/ddd/presentation/schema/health/__init__.py","description":"","nums":{"precision":0,"n_files":1,"n_statements":2,"n_excluded":0,"n_missing":0,"n_branches":0,"n_partial_branches":0,"n_missing_branches":0}}},"z_58015e6836bfb4e5_health_request_py":{"hash":"5b02858f5afdfe40e7b9d25b23639029","index":{"url":"z_58015e6836bfb4e5_health_request_py.html","file":"app/ddd/presentation/schema/health/health_request.py","description":"","nums":{"precision":0,"n_files":1,"n_statements":2,"n_excluded":1,"n_missing":0,"n_branches":0,"n_partial_branches":0,"n_missing_branches":0}}},"z_58015e6836bfb4e5_health_response_py":{"hash":"e4c0308c2d1796162fefe99850efc66f","index":{"url":"z_58015e6836bfb4e5_health_response_py.html","file":"app/ddd/presentation/schema/health/health_response.py","description":"","nums":{"precision":0,"n_files":1,"n_statements":3,"n_excluded":0,"n_missing":0,"n_branches":0,"n_partial_branches":0,"n_missing_branches":0}}},"z_c99aaa459d63ea18___init___py":{"hash":"688c94c65eec214634aaf60cfeab9aee","index":{"url":"z_c99aaa459d63ea18___init___py.html","file":"app/ddd/presentation/schema/user/__init__.py","description":"","nums":{"precision":0,"n_files":1,"n_statements":2,"n_excluded":0,"n_missing":0,"n_branches":0,"n_partial_branches":0,"n_missing_branches":0}}},"z_c99aaa459d63ea18_user_request_py":{"hash":"a0cfc6e923928518dde5878682605449","index":{"url":"z_c99aaa459d63ea18_user_request_py.html","file":"app/ddd/presentation/schema/user/user_request.py","description":"","nums":{"precision":0,"n_files":1,"n_statements":10,"n_excluded":3,"n_missing":0,"n_branches":0,"n_partial_branches":0,"n_missing_branches":0}}},"z_c99aaa459d63ea18_user_response_py":{"hash":"700765e1f342772b6a0a4c170b7a3d3a","index":{"url":"z_c99aaa459d63ea18_user_response_py.html","file":"app/ddd/presentation/schema/user/user_response.py","description":"","nums":{"precision":0,"n_files":1,"n_statements":12,"n_excluded":1,"n_missing":0,"n_branches":0,"n_partial_branches":0,"n_missing_branches":0}}},"z_5f5a17c013354698_main_py":{"hash":"960c6b09ed9ef309dec9570cbae8d5d8","index":{"url":"z_5f5a17c013354698_main_py.html","file":"app/main.py","description":"","nums":{"precision":0,"n_files":1,"n_statements":11,"n_excluded":0,"n_missing":0,"n_branches":0,"n_partial_branches":0,"n_missing_branches":0}}}}}